Intense_Simplicity.zip
README.txt
alterootheme.intensesimplicity-configure.zcml
setup.cfg
setup.py
alterootheme/__init__.py
alterootheme.intensesimplicity.egg-info/PKG-INFO
alterootheme.intensesimplicity.egg-info/SOURCES.txt
alterootheme.intensesimplicity.egg-info/dependency_links.txt
alterootheme.intensesimplicity.egg-info/entry_points.txt
alterootheme.intensesimplicity.egg-info/namespace_packages.txt
alterootheme.intensesimplicity.egg-info/not-zip-safe
alterootheme.intensesimplicity.egg-info/paster_plugins.txt
alterootheme.intensesimplicity.egg-info/requires.txt
alterootheme.intensesimplicity.egg-info/top_level.txt
alterootheme/intensesimplicity/__init__.py
alterootheme/intensesimplicity/configure.zcml
alterootheme/intensesimplicity/profiles.zcml
alterootheme/intensesimplicity/setuphandlers.py
alterootheme/intensesimplicity/skins.zcml
alterootheme/intensesimplicity/tests.py
alterootheme/intensesimplicity/todo.txt
alterootheme/intensesimplicity/version.txt
alterootheme/intensesimplicity/browser/__init__.py
alterootheme/intensesimplicity/browser/__init__.pyo
alterootheme/intensesimplicity/browser/configure.zcml
alterootheme/intensesimplicity/browser/interfaces.py
alterootheme/intensesimplicity/browser/viewlet.pt
alterootheme/intensesimplicity/browser/viewlets.py
alterootheme/intensesimplicity/browser/images/arrow.gif
alterootheme/intensesimplicity/browser/images/bodybg.png
alterootheme/intensesimplicity/browser/images/container_b.gif
alterootheme/intensesimplicity/browser/images/contentbg.gif
alterootheme/intensesimplicity/browser/images/dottedborder.gif
alterootheme/intensesimplicity/browser/images/dottedborder_dark.gif
alterootheme/intensesimplicity/browser/images/image.gif
alterootheme/intensesimplicity/browser/images/blockquote/exclamation.gif
alterootheme/intensesimplicity/browser/images/blockquote/go.gif
alterootheme/intensesimplicity/browser/images/blockquote/quote.gif
alterootheme/intensesimplicity/browser/images/blockquote/stop.gif
alterootheme/intensesimplicity/browser/images/corners/bl.gif
alterootheme/intensesimplicity/browser/images/corners/br.gif
alterootheme/intensesimplicity/browser/images/corners/l_bl.gif
alterootheme/intensesimplicity/browser/images/corners/l_br.gif
alterootheme/intensesimplicity/browser/images/corners/l_tl.gif
alterootheme/intensesimplicity/browser/images/corners/l_tr.gif
alterootheme/intensesimplicity/browser/images/corners/tl.gif
alterootheme/intensesimplicity/browser/images/corners/tr.gif
