Metadata-Version: 1.0
Name: alterootheme.intensesimplicity
Version: 1.0a
Summary: A Plone 3.0 Theme based on a free template by David Uliana
Home-page: http://themes.alteroo.com
Author: David Bain
Author-email: david.bain@alteroo.com
License: GPL
Keywords: web zope plone theme
Platform: UNKNOWN
Classifier: Framework :: Plone
Classifier: Framework :: Zope2
Classifier: Framework :: Zope3
Classifier: Programming Language :: Python
Classifier: Topic :: Software Development :: Libraries :: Python Modules
